requesck/SidraTools.py
requesck/__init__.py
requesck-1.0.dist-info/LICENSE
requesck-1.0.dist-info/METADATA
requesck-1.0.dist-info/WHEEL
requesck-1.0.dist-info/top_level.txt
requesck-1.0.dist-info/RECORD
